{"annotations": [{"id": ["NCBIGene:7471"], "is_neural_normalized": true, "mention": "Wnt", "obj": "gene", "prob": 0.9764117002487183, "span": {"begin": 106, "end": 109}}, {"id": ["CUI-less"], "is_neural_normalized": false, "mention": "Macrophages", "obj": "cell_type", "prob": 0.7890563011169434, "span": {"begin": 122, "end": 133}}, {"id": ["NCBIGene:64840"], "is_neural_normalized": true, "mention": "porcupine", "obj": "gene", "prob": 0.9542321562767029, "span": {"begin": 220, "end": 229}}, {"id": ["NCBIGene:7471"], "is_neural_normalized": true, "mention": "Wnt", "obj": "gene", "prob": 0.9916355609893799, "span": {"begin": 238, "end": 241}}, {"id": ["NCBIGene:7471"], "is_neural_normalized": true, "mention": "Wnt", "obj": "gene", "prob": 0.9695195555686951, "span": {"begin": 302, "end": 305}}, {"id": ["NCBIGene:1499"], "is_neural_normalized": false, "mention": "beta-catenin", "obj": "gene", "prob": 0.9909276962280273, "span": {"begin": 306, "end": 318}}], "text": "Sustained ROS increase caused by/causes DNA damage, which will alter several signaling pathways including Wnt signaling.  Macrophages accumulate into injured tissue to recover the tissue damage, which may be followed by porcupine-induced Wnt secretion. ROS stimulate inflammatory factor production and Wnt/beta-catenin signaling (Vall&eacute;e &amp; Lecarpentier, 2018).", "timestamp": "Mon Jun 08 15:20:26 +0000 2026"}