{"annotations": [{"id": ["mesh:D000086382"], "is_neural_normalized": false, "mention": "COVID-19", "obj": "disease", "prob": 0.9997872114181519, "span": {"begin": 74, "end": 82}}, {"id": ["NCBITaxon:9606"], "is_neural_normalized": false, "mention": "patients", "obj": "species", "prob": 0.9876695275306702, "span": {"begin": 83, "end": 91}}, {"id": ["NCBIGene:3827"], "is_neural_normalized": false, "mention": "bradykinin", "obj": "gene", "prob": 0.9727228283882141, "span": {"begin": 98, "end": 108}}, {"id": ["NCBIGene:3827"], "is_neural_normalized": true, "mention": "bradykininactivation", "obj": "gene", "prob": 0.9815828800201416, "span": {"begin": 418, "end": 438}}, {"id": ["CUI-less"], "is_neural_normalized": false, "mention": "SARS-", "obj": "species", "prob": 0.5995822548866272, "span": {"begin": 551, "end": 556}}, {"id": ["NCBITaxon:9606"], "is_neural_normalized": false, "mention": "human", "obj": "species", "prob": 0.9849938750267029, "span": {"begin": 573, "end": 578}}, {"id": ["NCBIGene:5054"], "is_neural_normalized": false, "mention": "PAI-1", "obj": "gene", "prob": 0.9909111857414246, "span": {"begin": 705, "end": 710}}, {"id": ["NCBIGene:5327"], "is_neural_normalized": false, "mention": "tPA", "obj": "gene", "prob": 0.9741109609603882, "span": {"begin": 715, "end": 718}}, {"id": ["mesh:D000347"], "is_neural_normalized": true, "mention": "hypofibrinolysis", "obj": "disease", "prob": 0.9999499320983887, "span": {"begin": 854, "end": 870}}, {"id": ["CUI-less"], "is_neural_normalized": false, "mention": "plasma", "obj": "cell_type", "prob": 0.49254369735717773, "span": {"begin": 881, "end": 887}}, {"id": ["NCBIGene:54938"], "is_neural_normalized": true, "mention": "SARS-COV-2", "obj": "gene", "prob": 0.9954654574394226, "span": {"begin": 1172, "end": 1182}}, {"id": ["NCBIGene:100128998"], "is_neural_normalized": false, "mention": "tissue plasminogen activator", "obj": "gene", "prob": 0.9899851679801941, "span": {"begin": 1259, "end": 1287}}, {"id": ["NCBIGene:5054"], "is_neural_normalized": false, "mention": "plasminogen activator inhibitor-1", "obj": "gene", "prob": 0.9976059794425964, "span": {"begin": 1292, "end": 1325}}, {"id": ["CUI-less"], "is_neural_normalized": false, "mention": "BAL", "obj": "cell_type", "prob": 0.525749146938324, "span": {"begin": 120, "end": 123}}, {"id": ["mesh:D001920"], "is_neural_normalized": false, "mention": "Bradykinin", "obj": "drug", "prob": 0.9308599233627319, "span": {"begin": 200, "end": 210}}, {"id": ["NCBIGene:623"], "is_neural_normalized": true, "mention": "Bradykinin(BK) receptors", "obj": "gene", "prob": 0.9411980509757996, "span": {"begin": 200, "end": 224}}, {"id": ["NCBIGene:623"], "is_neural_normalized": false, "mention": "BDKRB1", "obj": "gene", "prob": 0.902864396572113, "span": {"begin": 225, "end": 231}}, {"id": ["NCBIGene:624"], "is_neural_normalized": false, "mention": "BDKRB2", "obj": "gene", "prob": 0.977616012096405, "span": {"begin": 236, "end": 242}}, {"id": ["NCBIGene:3827"], "is_neural_normalized": true, "mention": "BK precursor", "obj": "gene", "prob": 0.8935835361480713, "span": {"begin": 315, "end": 327}}, {"id": ["NCBIGene:3827"], "is_neural_normalized": true, "mention": "kininogen", "obj": "gene", "prob": 0.6292219758033752, "span": {"begin": 328, "end": 337}}, {"id": ["NCBIGene:9622"], "is_neural_normalized": true, "mention": "kallikreins", "obj": "gene", "prob": 0.9807335138320923, "span": {"begin": 346, "end": 357}}, {"id": ["NCBIGene:710"], "is_neural_normalized": false, "mention": "SERPING1 gene", "obj": "gene", "prob": 0.99532550573349, "span": {"begin": 454, "end": 467}}, {"id": ["NCBIGene:623"], "is_neural_normalized": true, "mention": "bradykinin receptors 1 and 2", "obj": "gene", "prob": 0.9969989061355591, "span": {"begin": 586, "end": 614}}, {"id": ["NCBIGene:118471"], "is_neural_normalized": false, "mention": "uPA", "obj": "gene", "prob": 0.9971398711204529, "span": {"begin": 683, "end": 686}}, {"id": ["CUI-less"], "is_neural_normalized": false, "mention": "BDKRB2", "obj": "DNA", "prob": 0.5692030191421509, "span": {"begin": 777, "end": 783}}, {"id": ["NCBIGene:624", "623"], "is_neural_normalized": true, "mention": "BDKRB2 -&gt", "obj": "gene", "prob": 0.8295838236808777, "span": {"begin": 777, "end": 788}}, {"id": ["NCBIGene:3827"], "is_neural_normalized": true, "mention": "BK", "obj": "gene", "prob": null, "span": {"begin": 790, "end": 792}}, {"id": ["NCBIGene:6237"], "is_neural_normalized": true, "mention": "RAS", "obj": "gene", "prob": 0.9357456564903259, "span": {"begin": 1023, "end": 1026}}, {"id": ["NCBIGene:183"], "is_neural_normalized": true, "mention": "Angiotensin (1-9)", "obj": "gene", "prob": 0.9962607622146606, "span": {"begin": 0, "end": 17}}, {"id": ["NCBITaxon:10116"], "is_neural_normalized": false, "mention": "Wistar rats", "obj": "species", "prob": 0.6604174375534058, "span": {"begin": 34, "end": 45}}, {"id": ["NCBIGene:221264"], "is_neural_normalized": true, "mention": "Ang-(1&ndash;9)", "obj": "gene", "prob": 0.9968019127845764, "span": {"begin": 94, "end": 109}}, {"id": ["NCBIGene:9068", "51378", "738"], "is_neural_normalized": true, "mention": "ANG1-9", "obj": "gene", "prob": 0.9872963428497314, "span": {"begin": 300, "end": 306}}, {"id": ["NCBITaxon:10116"], "is_neural_normalized": false, "mention": "rats", "obj": "species", "prob": 0.9877445101737976, "span": {"begin": 310, "end": 314}}, {"id": ["NCBIGene:183"], "is_neural_normalized": true, "mention": "Angiotensin-(1-9)", "obj": "gene", "prob": 0.9977555274963379, "span": {"begin": 494, "end": 511}}, {"id": ["mesh:D020246"], "is_neural_normalized": true, "mention": "venous thrombosis", "obj": "disease", "prob": 0.99996417760849, "span": {"begin": 536, "end": 553}}, {"id": ["NCBITaxon:10116"], "is_neural_normalized": false, "mention": "rat", "obj": "species", "prob": 0.989801824092865, "span": {"begin": 561, "end": 564}}, {"id": ["NCBIGene:183"], "is_neural_normalized": true, "mention": "Renin Angiotensin", "obj": "gene", "prob": 0.5966787338256836, "span": {"begin": 610, "end": 627}}, {"id": ["mesh:D000809"], "is_neural_normalized": false, "mention": "Angiotensin", "obj": "drug", "prob": 0.5260216593742371, "span": {"begin": 616, "end": 627}}, {"id": ["mesh:D000450"], "is_neural_normalized": false, "mention": "Aldosterone", "obj": "drug", "prob": 0.974880039691925, "span": {"begin": 628, "end": 639}}, {"id": ["CUI-less"], "is_neural_normalized": false, "mention": "PMID:", "obj": "DNA", "prob": 0.5327292084693909, "span": {"begin": 717, "end": 722}}, {"id": ["NCBIGene:54938"], "is_neural_normalized": true, "mention": "SARS-COV-2            human", "obj": "gene", "prob": 0.8911951184272766, "span": {"begin": 733, "end": 760}}, {"id": ["NCBIGene:59272"], "is_neural_normalized": false, "mention": "ACE2", "obj": "gene", "prob": 0.9920561909675598, "span": {"begin": 808, "end": 812}}, {"id": ["NCBIGene:623"], "is_neural_normalized": true, "mention": "bradykinin receptor", "obj": "gene", "prob": 0.9972546696662903, "span": {"begin": 837, "end": 856}}, {"id": ["NCBIGene:5054"], "is_neural_normalized": true, "mention": "PAI-1 inhibitor", "obj": "gene", "prob": 0.9068228602409363, "span": {"begin": 993, "end": 1008}}, {"id": ["NCBIGene:285"], "is_neural_normalized": true, "mention": "Ang II", "obj": "gene", "prob": 0.9978894591331482, "span": {"begin": 1127, "end": 1133}}, {"id": ["NCBIGene:183"], "is_neural_normalized": false, "mention": "Angiotensin II", "obj": "gene", "prob": 0.9920449256896973, "span": {"begin": 1146, "end": 1160}}, {"id": ["mesh:D045169"], "is_neural_normalized": false, "mention": "SARS", "obj": "disease", "prob": 0.7685684561729431, "span": {"begin": 1286, "end": 1290}}, {"id": ["CUI-less"], "is_neural_normalized": false, "mention": "SARS-CoV-2", "obj": "species", "prob": 0.8093586564064026, "span": {"begin": 1286, "end": 1296}}, {"id": ["CUI-less"], "is_neural_normalized": false, "mention": "Human endothelial cells", "obj": "cell_type", "prob": 0.669407069683075, "span": {"begin": 68, "end": 91}}, {"id": ["NCBITaxon:9606"], "is_neural_normalized": false, "mention": "Human", "obj": "species", "prob": 0.9675269722938538, "span": {"begin": 68, "end": 73}}, {"id": ["NCBIGene:3569"], "is_neural_normalized": false, "mention": "IL6", "obj": "gene", "prob": 0.9641978144645691, "span": {"begin": 134, "end": 137}}, {"id": ["NCBIGene:10663"], "is_neural_normalized": true, "mention": "SIL6R", "obj": "gene", "prob": 0.9911119341850281, "span": {"begin": 158, "end": 163}}, {"id": ["NCBIGene:3827"], "is_neural_normalized": false, "mention": "Bradykinin", "obj": "gene", "prob": 0.8473079800605774, "span": {"begin": 175, "end": 185}}, {"id": ["NCBIGene:347365"], "is_neural_normalized": true, "mention": "ILl6", "obj": "gene", "prob": 0.9904470443725586, "span": {"begin": 284, "end": 288}}, {"id": ["NCBIGene:3565"], "is_neural_normalized": true, "mention": "tocilizumab", "obj": "gene", "prob": 0.8985313773155212, "span": {"begin": 418, "end": 429}}, {"id": ["NCBITaxon:9606"], "is_neural_normalized": false, "mention": "Patients", "obj": "species", "prob": 0.9689555764198303, "span": {"begin": 558, "end": 566}}, {"id": ["CUI-less"], "is_neural_normalized": false, "mention": "endothelial cells", "obj": "cell_type", "prob": 0.9087036848068237, "span": {"begin": 691, "end": 708}}, {"id": ["NCBIGene:3570"], "is_neural_normalized": false, "mention": "IL6R", "obj": "gene", "prob": 0.9954404830932617, "span": {"begin": 809, "end": 813}}, {"id": ["NCBIGene:3569"], "is_neural_normalized": false, "mention": "IL-6", "obj": "gene", "prob": 0.9936483502388, "span": {"begin": 1022, "end": 1026}}, {"id": ["CUI-less"], "is_neural_normalized": false, "mention": "vascular endothelial cells", "obj": "cell_type", "prob": 0.8965572714805603, "span": {"begin": 1090, "end": 1116}}, {"id": ["mesh:D000080424"], "is_neural_normalized": false, "mention": "cytokine release syndrome", "obj": "disease", "prob": 0.9999837875366211, "span": {"begin": 1120, "end": 1145}}, {"id": ["CUI-less"], "is_neural_normalized": false, "mention": "Adipose", "obj": "cell_type", "prob": 0.4731557071208954, "span": {"begin": 1288, "end": 1295}}, {"id": ["NCBIGene:3569"], "is_neural_normalized": false, "mention": "interleukin-6", "obj": "gene", "prob": 0.882092297077179, "span": {"begin": 353, "end": 366}}, {"id": ["NCBIGene:5196"], "is_neural_normalized": true, "mention": "oncostatin", "obj": "gene", "prob": 0.9904194474220276, "span": {"begin": 371, "end": 381}}, {"id": ["CUI-less"], "is_neural_normalized": false, "mention": "human adipose tissue", "obj": "cell_type", "prob": 0.5570151209831238, "span": {"begin": 428, "end": 448}}]}