{"annotations": [{"id": ["CUI-less"], "is_neural_normalized": false, "mention": "vascular smooth muscle cells", "obj": "cell_type", "prob": 0.8790413737297058, "span": {"begin": 44, "end": 72}}, {"id": ["mesh:D006152"], "is_neural_normalized": false, "mention": "cyclic GMP", "obj": "drug", "prob": 0.879389226436615, "span": {"begin": 169, "end": 179}}, {"id": ["mesh:D009569"], "is_neural_normalized": false, "mention": "NO", "obj": "drug", "prob": null, "span": {"begin": 227, "end": 229}}, {"id": ["mesh:D009569"], "is_neural_normalized": false, "mention": "NO", "obj": "drug", "prob": null, "span": {"begin": 252, "end": 254}}, {"id": ["mesh:D006940"], "is_neural_normalized": true, "mention": "vasodilation", "obj": "disease", "prob": 0.6542370915412903, "span": {"begin": 283, "end": 295}}, {"id": ["mesh:D009569"], "is_neural_normalized": false, "mention": "NO", "obj": "drug", "prob": null, "span": {"begin": 370, "end": 372}}, {"id": ["NCBIGene:4846"], "is_neural_normalized": false, "mention": "eNOS", "obj": "gene", "prob": 0.9808557629585266, "span": {"begin": 377, "end": 381}}, {"id": ["mesh:D000109"], "is_neural_normalized": false, "mention": "acetylcholine", "obj": "drug", "prob": 0.9709416627883911, "span": {"begin": 402, "end": 415}}, {"id": ["NCBIGene:207"], "is_neural_normalized": false, "mention": "AKT", "obj": "gene", "prob": 0.9892556667327881, "span": {"begin": 557, "end": 560}}, {"id": ["NCBIGene:4846"], "is_neural_normalized": false, "mention": "eNOS", "obj": "gene", "prob": 0.9873567819595337, "span": {"begin": 613, "end": 617}}, {"id": ["NCBITaxon:9986"], "is_neural_normalized": false, "mention": "rabbit", "obj": "species", "prob": 0.9624357223510742, "span": {"begin": 658, "end": 664}}, {"id": ["NCBIGene:4846"], "is_neural_normalized": false, "mention": "eNOS", "obj": "gene", "prob": 0.9856767654418945, "span": {"begin": 705, "end": 709}}, {"id": ["mesh:D019331"], "is_neural_normalized": false, "mention": "L-NAME", "obj": "drug", "prob": 0.9983208775520325, "span": {"begin": 720, "end": 726}}, {"id": ["NCBIGene:1607"], "is_neural_normalized": true, "mention": "Dominant negative AKT", "obj": "gene", "prob": 0.9960370659828186, "span": {"begin": 768, "end": 789}}, {"id": ["NCBIGene:4846"], "is_neural_normalized": false, "mention": "eNOS", "obj": "gene", "prob": 0.9875822067260742, "span": {"begin": 806, "end": 810}}, {"id": ["mesh:D000109"], "is_neural_normalized": false, "mention": "acetylcholine", "obj": "drug", "prob": 0.9946755170822144, "span": {"begin": 898, "end": 911}}, {"id": ["mesh:D000109"], "is_neural_normalized": false, "mention": "ACh", "obj": "drug", "prob": 0.9976882934570312, "span": {"begin": 913, "end": 916}}, {"id": ["NCBITaxon:9986"], "is_neural_normalized": false, "mention": "rabbit", "obj": "species", "prob": 0.9824677109718323, "span": {"begin": 921, "end": 927}}, {"id": ["NCBITaxon:10090"], "is_neural_normalized": false, "mention": "mouse", "obj": "species", "prob": 0.9818336367607117, "span": {"begin": 941, "end": 946}}, {"id": ["mesh:D000109"], "is_neural_normalized": false, "mention": "acetylcholine", "obj": "drug", "prob": 0.9934926629066467, "span": {"begin": 961, "end": 974}}, {"id": ["NCBIGene:4846"], "is_neural_normalized": false, "mention": "eNOS", "obj": "gene", "prob": 0.9837638139724731, "span": {"begin": 1047, "end": 1051}}, {"id": ["mesh:D000109"], "is_neural_normalized": false, "mention": "Ach", "obj": "drug", "prob": 0.9926761984825134, "span": {"begin": 1070, "end": 1073}}, {"id": ["mesh:D009569"], "is_neural_normalized": false, "mention": "NO", "obj": "drug", "prob": null, "span": {"begin": 1096, "end": 1098}}, {"id": ["mesh:D019331"], "is_neural_normalized": false, "mention": "L-NAME", "obj": "drug", "prob": 0.998849630355835, "span": {"begin": 1153, "end": 1159}}, {"id": ["mesh:D000109"], "is_neural_normalized": false, "mention": "ACh", "obj": "drug", "prob": 0.6992678046226501, "span": {"begin": 1215, "end": 1218}}, {"id": ["NCBIGene:1911"], "is_neural_normalized": false, "mention": "hph-1", "obj": "gene", "prob": 0.9943934679031372, "span": {"begin": 1246, "end": 1251}}, {"id": ["NCBITaxon:10095"], "is_neural_normalized": false, "mention": "mice", "obj": "species", "prob": 0.9712101221084595, "span": {"begin": 1252, "end": 1256}}, {"id": ["mesh:D000109"], "is_neural_normalized": false, "mention": "ACh", "obj": "drug", "prob": 0.9990861415863037, "span": {"begin": 1276, "end": 1279}}, {"id": ["NCBITaxon:10116"], "is_neural_normalized": false, "mention": "rat", "obj": "species", "prob": 0.9873107671737671, "span": {"begin": 1341, "end": 1344}}, {"id": ["mesh:D009569"], "is_neural_normalized": false, "mention": "NO", "obj": "drug", "prob": null, "span": {"begin": 1380, "end": 1382}}, {"id": ["mesh:D000109"], "is_neural_normalized": false, "mention": "ACh", "obj": "drug", "prob": 0.998712420463562, "span": {"begin": 1406, "end": 1409}}, {"id": ["mesh:D019331"], "is_neural_normalized": false, "mention": "L-NAME", "obj": "drug", "prob": 0.9993327260017395, "span": {"begin": 1446, "end": 1452}}, {"id": ["NCBITaxon:10116"], "is_neural_normalized": false, "mention": "rats", "obj": "species", "prob": 0.9830085039138794, "span": {"begin": 1461, "end": 1465}}, {"id": ["mesh:D019331"], "is_neural_normalized": false, "mention": "L-NAME", "obj": "drug", "prob": 0.9994854927062988, "span": {"begin": 1495, "end": 1501}}, {"id": ["mesh:D009569"], "is_neural_normalized": false, "mention": "NO", "obj": "drug", "prob": null, "span": {"begin": 1517, "end": 1519}}, {"id": ["mesh:D019331"], "is_neural_normalized": false, "mention": "L-NAME", "obj": "drug", "prob": 0.9979569315910339, "span": {"begin": 1578, "end": 1584}}, {"id": ["NCBIGene:4846"], "is_neural_normalized": false, "mention": "eNOS", "obj": "gene", "prob": 0.9866622090339661, "span": {"begin": 1596, "end": 1600}}, {"id": ["NCBIGene:4842"], "is_neural_normalized": false, "mention": "NOS", "obj": "gene", "prob": 0.9883914589881897, "span": {"begin": 1643, "end": 1646}}, {"id": ["NCBITaxon:10116"], "is_neural_normalized": false, "mention": "rat", "obj": "species", "prob": 0.9895037412643433, "span": {"begin": 1677, "end": 1680}}, {"id": ["mesh:D019331"], "is_neural_normalized": false, "mention": "L-NAME", "obj": "drug", "prob": 0.9994292259216309, "span": {"begin": 1715, "end": 1721}}, {"id": ["NCBITaxon:10116"], "is_neural_normalized": false, "mention": "rat", "obj": "species", "prob": 0.9895791411399841, "span": {"begin": 1780, "end": 1783}}], "text": "Vasodilation is caused by the relaxation of vascular smooth muscle cells within the walls of blood vessels, which is regulated through a number of mechanisms, including cyclic GMP-dependent hyperpolarization and relaxation via NO. Thus, alterations to NO levels have an influence on vasodilation (Silva et al., 2012). Many animal studies demonstrated that inhibition of NO via eNOS inhibitors impaired acetylcholine-induced endothelium-dependent vasodilation, providing strong biological plausibility for this key event relationship.  Constitutively active AKT, which has been shown to phosphorylate and activate eNOS, increased resting vessel diameter in a rabbit femoral artery model, but infusion with eNOS inhibitor L-NAME reversed this effect (Luo et al., 2000). Dominant negative AKT, which prevents eNOS activation, also blocked vasodilation in response to the endothelium-dependent agonist acetylcholine (ACh) in rabbit arteries and mouse aortas. Since acetylcholine induces endothelium-dependent vasodilation, the assumption is that when eNOS inhibitors blocks Ach-induced vasodilation, NO production is decreased and vasodilation is impaired. L-NAME abolished endothelium-dependent relaxations induced by ACh in aortas of wild-type and hph-1 mice (Li et al., 2007). ACh induced a dose-dependent endothelium-dependent relaxation in rat small mesenteric arteries, but the NO-dependent component of ACh-induced relaxation was decreased in L-NAME-treated rats (Paulis et al., 2008). After L-NAME cessation, the NO-dependent component was restored to above control levels. L-NAME diminished eNOS activity by 66% and its cessation restore NOS activity to control levels in rat aortas. Another study showed that L-NAME caused a mild but significant decrease in vasodilation in rat thoracic aorta (S&eacute;lley et al., 2014).", "timestamp": "Mon Jun 08 14:53:02 +0000 2026"}