{"annotations": [{"id": ["CUI-less"], "is_neural_normalized": false, "mention": "photoreceptor subtypes", "obj": "cell_type", "prob": 0.7602623701095581, "span": {"begin": 16, "end": 38}}, {"id": ["NCBIGene:5956"], "is_neural_normalized": true, "mention": "opsins", "obj": "gene", "prob": 0.9834234714508057, "span": {"begin": 54, "end": 60}}, {"id": ["CUI-less"], "is_neural_normalized": false, "mention": "photoreceptor subtypes", "obj": "cell_type", "prob": 0.7292869091033936, "span": {"begin": 216, "end": 238}}], "text": "Since different photoreceptor subtypes have different opsins that allow for perceiving light of different wavelengths, it is plausible to assume that alterations in photoreceptor patterning such as altered ratios of photoreceptor subtypes affect normal visual function.   &nbsp;", "timestamp": "Mon Jun 08 15:20:21 +0000 2026"}