{"annotations": [{"id": ["CUI-less"], "is_neural_normalized": false, "mention": "DNA", "obj": "DNA", "prob": 0.5183478593826294, "span": {"begin": 55, "end": 58}}, {"id": ["CUI-less"], "is_neural_normalized": false, "mention": "actively proliferating germ cells", "obj": "cell_type", "prob": 0.7469207048416138, "span": {"begin": 95, "end": 128}}, {"id": ["CUI-less"], "is_neural_normalized": false, "mention": "spermatogonia", "obj": "cell_type", "prob": 0.8920077681541443, "span": {"begin": 143, "end": 156}}, {"id": ["CUI-less"], "is_neural_normalized": false, "mention": "differentiating germ cell populations", "obj": "cell_type", "prob": 0.8883525729179382, "span": {"begin": 470, "end": 507}}, {"id": ["CL:0000019"], "is_neural_normalized": false, "mention": "sperm", "obj": "cell_type", "prob": 0.46265628933906555, "span": {"begin": 535, "end": 540}}], "text": "DNA alkylating agents can form covalent adducts in the DNA of any exposed cell types; however, actively proliferating germ cells, particularly spermatogonia, are especially susceptible to the cytotoxic consequences of alkylation damage. During DNA replication, alkyl adducts can interfere with replication fork progression and activate DNA damage response pathways. Persistent or unrepaired lesions can result in cell cycle arrest and apoptosis, leading to depletion of differentiating germ cell populations and, consequently, reduced sperm production.", "timestamp": "Sat Jul 04 10:31:23 +0000 2026"}