{"annotations": [{"id": ["NCBIGene:43"], "is_neural_normalized": false, "mention": "AChE", "obj": "gene", "prob": 0.9841911792755127, "span": {"begin": 42, "end": 46}}, {"id": ["mesh:D000109"], "is_neural_normalized": false, "mention": "acetylcholine", "obj": "drug", "prob": 0.9038244485855103, "span": {"begin": 139, "end": 152}}, {"id": ["CUI-less"], "is_neural_normalized": false, "mention": "cardiomyocytes", "obj": "cell_type", "prob": 0.81259685754776, "span": {"begin": 165, "end": 179}}, {"id": ["mesh:D000109"], "is_neural_normalized": false, "mention": "Acetylcholine", "obj": "drug", "prob": 0.9979085922241211, "span": {"begin": 194, "end": 207}}, {"id": ["NCBIGene:1128"], "is_neural_normalized": true, "mention": "muscarinic receptors", "obj": "gene", "prob": 0.9584947228431702, "span": {"begin": 216, "end": 236}}, {"id": ["NCBIGene:1128"], "is_neural_normalized": true, "mention": "muscarinic receptor", "obj": "gene", "prob": 0.9953439235687256, "span": {"begin": 282, "end": 301}}, {"id": ["NCBIGene:1129"], "is_neural_normalized": true, "mention": "M2", "obj": "gene", "prob": 0.9977278113365173, "span": {"begin": 303, "end": 305}}, {"id": ["mesh:D001919"], "is_neural_normalized": false, "mention": "bradycardia", "obj": "disease", "prob": 0.9996488094329834, "span": {"begin": 316, "end": 327}}, {"id": ["NCBITaxon:9606"], "is_neural_normalized": false, "mention": "humans", "obj": "species", "prob": 0.9706689119338989, "span": {"begin": 331, "end": 337}}], "text": "The cardiovascular system is sensitive to AChE inhibition due to vagal innervation of heart tissue and due to the presence of non-neuronal acetylcholine released by cardiomyocytes in the heart. Acetylcholine acts on muscarinic receptors in the heart and overstimulation of the main muscarinic receptor (M2) leads to bradycardia in humans and in fish (Costa, Duagsawasdi 1978, Hsieh, 2002).", "timestamp": "Mon Jun 08 14:29:33 +0000 2026"}