{"annotations": [{"id": ["mesh:D007249"], "is_neural_normalized": false, "mention": "inflammation", "obj": "disease", "prob": 0.9948967099189758, "span": {"begin": 288, "end": 300}}], "text": "Biological state: cell death resulting from cellular swelling, as opposed to apoptosis.  Biological compartment: tissue level -- cellular swelling and death.  General role in biology: oncotic necrosis is cell death that is not planned or programmed. Oncotic necrosis typically results in inflammation.", "timestamp": "Fri May 15 21:42:07 +0000 2026"}