{"annotations": [{"id": ["CUI-less"], "is_neural_normalized": false, "mention": "angioblast precursors", "obj": "cell_type", "prob": 0.8339107632637024, "span": {"begin": 104, "end": 125}}, {"id": ["CUI-less"], "is_neural_normalized": false, "mention": "angioblasts", "obj": "cell_type", "prob": 0.8836910724639893, "span": {"begin": 385, "end": 396}}, {"id": ["CUI-less"], "is_neural_normalized": false, "mention": "endothelial and mural cell progenitor populations", "obj": "cell_type", "prob": 0.8789124488830566, "span": {"begin": 449, "end": 498}}], "text": "The formation of new blood vessels during development occurs via de novo assembly of blood vessels from angioblast precursors (vasculogenesis) and formation of new capillary sprouts from preexisting vessels (angiogenesis) (Ivnitski-Steele and Walker 2005). The epicardium is a single cell layer that spreads over the surface of the heart during embryo development and is the source of angioblasts, which penetrate into the myocardium, providing the endothelial and mural cell progenitor populations that eventually form the entire coronary vasculature (Ivnitski-Steele and Walker 2005; Viragh et al. 1993; Vrancken Peeters et al. 1999). The development of the vasculature into highly branched conduits needs to occur in numerous sites and in precise patterns to supply oxygen and nutrients to the rapidly expanding tissue of the embryo; aberrant regulation and coordination of angiogenic signals during development result in impaired organ development (Chung and Ferrara 2011).", "timestamp": "Mon Jun 08 14:53:56 +0000 2026"}