{"annotations": [{"id": ["mesh:D009569"], "is_neural_normalized": false, "mention": "NO", "obj": "drug", "prob": null, "span": {"begin": 187, "end": 189}}, {"id": ["mesh:D019323"], "is_neural_normalized": false, "mention": "L-NMMA", "obj": "drug", "prob": 0.9992777705192566, "span": {"begin": 227, "end": 233}}, {"id": ["mesh:D009569"], "is_neural_normalized": false, "mention": "NO", "obj": "drug", "prob": null, "span": {"begin": 306, "end": 308}}, {"id": ["NCBITaxon:10116"], "is_neural_normalized": false, "mention": "rat", "obj": "species", "prob": 0.9781190156936646, "span": {"begin": 381, "end": 384}}, {"id": ["mesh:D019331"], "is_neural_normalized": false, "mention": "L-NAME", "obj": "drug", "prob": 0.9996178150177002, "span": {"begin": 427, "end": 433}}, {"id": ["mesh:D009569"], "is_neural_normalized": false, "mention": "NO", "obj": "drug", "prob": null, "span": {"begin": 459, "end": 461}}, {"id": ["mesh:D009569"], "is_neural_normalized": false, "mention": "NO", "obj": "drug", "prob": null, "span": {"begin": 675, "end": 677}}, {"id": ["mesh:D009599"], "is_neural_normalized": false, "mention": "sodium nitroprusside", "obj": "drug", "prob": 0.9993396997451782, "span": {"begin": 684, "end": 704}}, {"id": ["NCBITaxon:9606"], "is_neural_normalized": false, "mention": "women", "obj": "species", "prob": 0.8706455230712891, "span": {"begin": 809, "end": 814}}, {"id": ["mesh:D006973"], "is_neural_normalized": false, "mention": "hypertension", "obj": "disease", "prob": 0.9994183778762817, "span": {"begin": 834, "end": 846}}, {"id": ["mesh:D006973"], "is_neural_normalized": false, "mention": "hypertensive", "obj": "disease", "prob": 0.7583887577056885, "span": {"begin": 870, "end": 882}}, {"id": ["mesh:D005352"], "is_neural_normalized": false, "mention": "FMD", "obj": "disease", "prob": 0.9991764426231384, "span": {"begin": 925, "end": 928}}, {"id": ["NCBITaxon:9606"], "is_neural_normalized": false, "mention": "women", "obj": "species", "prob": 0.9682762622833252, "span": {"begin": 947, "end": 952}}, {"id": ["NCBITaxon:9606"], "is_neural_normalized": false, "mention": "women", "obj": "species", "prob": 0.9737682938575745, "span": {"begin": 969, "end": 974}}, {"id": ["mesh:D005352"], "is_neural_normalized": false, "mention": "FMD", "obj": "disease", "prob": 0.9968382120132446, "span": {"begin": 976, "end": 979}}, {"id": ["mesh:D006940"], "is_neural_normalized": true, "mention": "vasodilation", "obj": "disease", "prob": 0.6428357362747192, "span": {"begin": 1101, "end": 1113}}, {"id": ["mesh:D006973"], "is_neural_normalized": false, "mention": "hypertension", "obj": "disease", "prob": 0.9998854398727417, "span": {"begin": 1118, "end": 1130}}, {"id": ["mesh:D009569"], "is_neural_normalized": false, "mention": "NO", "obj": "drug", "prob": null, "span": {"begin": 1233, "end": 1235}}, {"id": ["mesh:D005352"], "is_neural_normalized": false, "mention": "FMD", "obj": "disease", "prob": 0.9999650716781616, "span": {"begin": 1304, "end": 1307}}, {"id": ["mesh:D009569"], "is_neural_normalized": false, "mention": "NO", "obj": "drug", "prob": null, "span": {"begin": 1466, "end": 1468}}], "text": "Include consideration of temporal concordance here   No direct evidence was found for this linkage; thus the empirical support is weak. One study indirectly showed a relationship between NO depletion and SVR, where infusion of L-NMMA (1.0 mg/kg/min) caused an increase in SVR by 63% and a 65% reduction in NO in 11 healthy volunteers after three minutes (Stamler et al., 1994). In rat small mesenteric arteries, treatment with L-NAME for five weeks decreased NO-dependent relaxation from 30% to less than 10%, but increased systolic and diastolic blood pressure to 26% and 40%, respectively (Paulis et al, 2008). Meta-analysis of clinical trials showing that infusion of the NO donor sodium nitroprusside led to a dose-dependent reduction in SVR (Eugene et al., 2016).&nbsp; In a study of 400 post-menopausal women with mild-moderate hypertension and impaired FMD, anti-hypertensive therapy for 6 months was shown to improve FMD by &gt;10% in 250 women, whereas in 150 women, FMD did not significantly change (&lt;10% change, Modena et al. 2002).&nbsp; Whilst the study demonstrates a linkage between vasodilation and hypertension in a large proportion of the study population, it raises a&nbsp;question regarding causality i.e. did NO-independent medication lower blood pressure, which in turn improved FMD?&nbsp; Furthermore, over a third of the population showed no change.&nbsp; It is possible that the medications used directly influenced key components of the NO (or other) pathways.&nbsp; Since the study did not elaborate on the medicatons used by the study cohort, this is impossible to determine.", "timestamp": "Mon Jun 08 14:53:09 +0000 2026"}