{"annotations": [{"id": ["CUI-less"], "is_neural_normalized": false, "mention": "astrocytes", "obj": "cell_type", "prob": 0.7991081476211548, "span": {"begin": 359, "end": 369}}, {"id": ["CUI-less"], "is_neural_normalized": false, "mention": "astrocytes", "obj": "cell_type", "prob": 0.8046625852584839, "span": {"begin": 380, "end": 390}}, {"id": ["NCBIGene:1733"], "is_neural_normalized": true, "mention": "deiodinase", "obj": "gene", "prob": 0.976093590259552, "span": {"begin": 417, "end": 427}}, {"id": ["CUI-less"], "is_neural_normalized": false, "mention": "neurons", "obj": "cell_type", "prob": 0.7746782302856445, "span": {"begin": 460, "end": 467}}, {"id": ["CUI-less"], "is_neural_normalized": false, "mention": "genes", "obj": "DNA", "prob": 0.8436912894248962, "span": {"begin": 558, "end": 563}}], "text": "It is widely accepted that the thyroid hormones (TH) play a prominent role in the development and function of the CNS, including hippocampus and neocortex, two critical brain structure closely linked to the cognitive function (Gilbert et al., 2012). Brain concentrations of T4 are dependent on transfer of T4 from serum, through the vascular endothelia, into astrocytes.&nbsp; In astrocytes, T4 is converted to T3 by deiodinase and subsequently transferred to neurons cellular membrane transporters. In the brain T3 controls transcription and translation of genes responsible for normal hippocampal structural and functional development. Normal hippocampal structure and physiology are critical for the development of cognitive function. Thus, there is an indisputable indirect link between TH synthesis, controlling the levels of T4 in serum, and cognitive function, including learning and memory processes.", "timestamp": "Mon Jun 08 14:46:08 +0000 2026"}