{"annotations": [{"id": ["CUI-less"], "is_neural_normalized": false, "mention": "male", "obj": "cell_type", "prob": 0.43338796496391296, "span": {"begin": 170, "end": 174}}, {"id": ["NCBIGene:367", "231", "2232"], "is_neural_normalized": true, "mention": "AR", "obj": "gene", "prob": null, "span": {"begin": 243, "end": 245}}, {"id": ["mesh:D005278"], "is_neural_normalized": false, "mention": "fenitrothion", "obj": "drug", "prob": 0.9996981620788574, "span": {"begin": 256, "end": 268}}, {"id": ["mesh:D005485"], "is_neural_normalized": false, "mention": "flutamide", "obj": "drug", "prob": 0.9957342743873596, "span": {"begin": 270, "end": 279}}, {"id": ["mesh:D008044"], "is_neural_normalized": false, "mention": "linuron", "obj": "drug", "prob": 0.9975816011428833, "span": {"begin": 281, "end": 288}}, {"id": ["mesh:C013099"], "is_neural_normalized": false, "mention": "mancozeb", "obj": "drug", "prob": 0.9991157650947571, "span": {"begin": 290, "end": 298}}, {"id": ["mesh:C061077"], "is_neural_normalized": true, "mention": "pp&rsquo;-DDE", "obj": "drug", "prob": 0.9991305470466614, "span": {"begin": 300, "end": 313}}, {"id": ["mesh:C045362"], "is_neural_normalized": false, "mention": "prochloraz", "obj": "drug", "prob": 0.9984942674636841, "span": {"begin": 315, "end": 325}}, {"id": ["mesh:C035988"], "is_neural_normalized": false, "mention": "procymidone", "obj": "drug", "prob": 0.9985275268554688, "span": {"begin": 327, "end": 338}}, {"id": ["mesh:C581681"], "is_neural_normalized": false, "mention": "pyrifluquinazon", "obj": "drug", "prob": 0.998683512210846, "span": {"begin": 340, "end": 355}}, {"id": ["mesh:C087114"], "is_neural_normalized": false, "mention": "tebuconazole", "obj": "drug", "prob": 0.9990918636322021, "span": {"begin": 357, "end": 369}}, {"id": ["mesh:C025643"], "is_neural_normalized": false, "mention": "vinclozolin", "obj": "drug", "prob": 0.9990602135658264, "span": {"begin": 374, "end": 385}}, {"id": ["NCBITaxon:10116"], "is_neural_normalized": false, "mention": "rats", "obj": "species", "prob": 0.9771390557289124, "span": {"begin": 518, "end": 522}}, {"id": ["NCBITaxon:10095"], "is_neural_normalized": false, "mention": "mice", "obj": "species", "prob": 0.992284893989563, "span": {"begin": 577, "end": 581}}, {"id": ["CUI-less"], "is_neural_normalized": false, "mention": "offspring", "obj": "cell_type", "prob": 0.4773494601249695, "span": {"begin": 900, "end": 909}}, {"id": ["NCBITaxon:10095"], "is_neural_normalized": false, "mention": "mice", "obj": "species", "prob": 0.9479629993438721, "span": {"begin": 1454, "end": 1458}}, {"id": ["NCBITaxon:10116"], "is_neural_normalized": false, "mention": "rats", "obj": "species", "prob": 0.989362895488739, "span": {"begin": 1521, "end": 1525}}, {"id": ["mesh:D007775"], "is_neural_normalized": true, "mention": "nipple retention", "obj": "disease", "prob": 0.9970016479492188, "span": {"begin": 1839, "end": 1855}}, {"id": ["NCBIGene:367", "231", "2232"], "is_neural_normalized": true, "mention": "AR", "obj": "gene", "prob": null, "span": {"begin": 1978, "end": 1980}}], "text": "The empirical support from studies in animals for this KER is judged as high overall.  The relationship is supported by numerous studies demonstrating induction of NR in male offspring after in utero exposure to substances known to antagonise AR in vitro (fenitrothion, flutamide, linuron, mancozeb, pp&rsquo;-DDE, prochloraz, procymidone, pyrifluquinazon, tebuconazole and vinclozolin) (Pedersen et al., 2022; Appendix 1, 12h4h48cc2_KER_2133_Appendix_1.pdf). The empirical evidence includes only studies conducted in rats, although it is believed that the link also exists in mice, and &nbsp;other rodent species (Pedersen et al., 2022). &nbsp;Some inconsistences in the empirical evidence for 3 of the substances were observed. These could, however, be explained by differences in dose levels, and the level of confidence for prenatal exposure to these substances resulting in increased NR in male offspring is judged to be strong (Appendix 1,12h4h48cc2_KER_2133_Appendix_1.pdf).   Dose concordance  Dose concordance is challenging to assess for this KER since the upstream event is measured in vitro and the downstream event is measured in vivo.   Temporal concordance  Temporal concordance can only be considered from a theoretical perspective since the downstream event, &lsquo;increased NR&rsquo;, is a result of the disruption of the normal regression of nipple anlagen in male rodents induced during a short window of gestational development (in mice of approximately 2 days), but usually measured at PND12-14 in rats. Earlier than this, the areolae are not yet visible through the skin and later than this, the animals grow fur and need to be shaved for proper examination. This is supported by several of the studies in the empirical evidence, where the test substance was administered during a short period during gestation and nipple retention was observed postnatally.  Based on current knowledge, it is understood that the upstream event &ndash; antagonism of the AR&nbsp; &ndash; takes place minutes to hours after exposure to an anti-androgenic substance.", "timestamp": "Mon Jun 08 15:28:00 +0000 2026"}