{"annotations": [{"id": ["CUI-less"], "is_neural_normalized": false, "mention": "endothelial cells", "obj": "cell_type", "prob": 0.913616955280304, "span": {"begin": 189, "end": 206}}, {"id": ["CUI-less"], "is_neural_normalized": false, "mention": "pericytes", "obj": "cell_type", "prob": 0.8312965035438538, "span": {"begin": 275, "end": 284}}, {"id": ["CUI-less"], "is_neural_normalized": false, "mention": "Endothelial Cells", "obj": "cell_type", "prob": 0.9224828481674194, "span": {"begin": 541, "end": 558}}, {"id": ["CUI-less"], "is_neural_normalized": false, "mention": "Endothelial cells", "obj": "cell_type", "prob": 0.9041229486465454, "span": {"begin": 560, "end": 577}}, {"id": ["CUI-less"], "is_neural_normalized": false, "mention": "endothelial cells", "obj": "cell_type", "prob": 0.911979079246521, "span": {"begin": 753, "end": 770}}, {"id": ["CUI-less"], "is_neural_normalized": false, "mention": "Endothelial cells", "obj": "cell_type", "prob": 0.9237570762634277, "span": {"begin": 875, "end": 892}}, {"id": ["CUI-less"], "is_neural_normalized": false, "mention": "tube", "obj": "cell_line", "prob": 0.4853622019290924, "span": {"begin": 907, "end": 911}}, {"id": ["CUI-less"], "is_neural_normalized": false, "mention": "pericytes", "obj": "cell_type", "prob": 0.8137224912643433, "span": {"begin": 1117, "end": 1126}}, {"id": ["CUI-less"], "is_neural_normalized": false, "mention": "blood vessels", "obj": "cell_type", "prob": 0.5267244577407837, "span": {"begin": 1290, "end": 1303}}, {"id": ["NCBIGene:7422"], "is_neural_normalized": false, "mention": "VEGF", "obj": "gene", "prob": 0.996056079864502, "span": {"begin": 1526, "end": 1530}}, {"id": ["NCBIGene:2246"], "is_neural_normalized": true, "mention": "FGF", "obj": "gene", "prob": 0.9885567426681519, "span": {"begin": 1535, "end": 1538}}, {"id": ["mesh:D009369"], "is_neural_normalized": false, "mention": "cancer", "obj": "disease", "prob": 0.9999884366989136, "span": {"begin": 1677, "end": 1683}}, {"id": ["CUI-less"], "is_neural_normalized": false, "mention": "immune cells", "obj": "cell_type", "prob": 0.9138765335083008, "span": {"begin": 2381, "end": 2393}}, {"id": ["mesh:D009369"], "is_neural_normalized": false, "mention": "Cancer", "obj": "disease", "prob": 0.9989637136459351, "span": {"begin": 2428, "end": 2434}}, {"id": ["mesh:D009369"], "is_neural_normalized": false, "mention": "cancer", "obj": "disease", "prob": 0.9999634027481079, "span": {"begin": 2467, "end": 2473}}, {"id": ["mesh:D009369"], "is_neural_normalized": false, "mention": "tumors", "obj": "disease", "prob": 0.9999949932098389, "span": {"begin": 2503, "end": 2509}}, {"id": ["mesh:D009369"], "is_neural_normalized": false, "mention": "Tumors", "obj": "disease", "prob": 0.9998588562011719, "span": {"begin": 2550, "end": 2556}}, {"id": ["CUI-less"], "is_neural_normalized": false, "mention": "cancer cells", "obj": "cell_type", "prob": 0.4461255669593811, "span": {"begin": 2682, "end": 2694}}, {"id": ["mesh:D009369"], "is_neural_normalized": false, "mention": "cancer", "obj": "disease", "prob": 0.9995914101600647, "span": {"begin": 2682, "end": 2688}}, {"id": ["mesh:D017202"], "is_neural_normalized": true, "mention": "Ischemic Diseases", "obj": "disease", "prob": 0.9999959468841553, "span": {"begin": 2707, "end": 2724}}, {"id": ["mesh:D003324"], "is_neural_normalized": true, "mention": "ischemic heart disease", "obj": "disease", "prob": 0.9999982714653015, "span": {"begin": 2818, "end": 2840}}, {"id": ["mesh:D058729"], "is_neural_normalized": false, "mention": "peripheral artery disease", "obj": "disease", "prob": 0.9999955296516418, "span": {"begin": 2845, "end": 2870}}], "text": "Angiogenesis is the physiological process through which new blood vessels form from existing vessels. This complex and tightly regulated process involves the proliferation and migration of endothelial cells, the remodeling of the extracellular matrix, and the recruitment of pericytes and smooth muscle cells.   &nbsp;  Key Steps in Angiogenesis:    Stimulus for Angiogenesis: Angiogenesis is triggered by specific signals, such as growth factors, released in response to tissue hypoxia, injury, or other physiological needs.  Activation of Endothelial Cells: Endothelial cells in existing blood vessels become activated in response to angiogenic signals, leading to changes in gene expression and cell behavior.  Proliferation and Migration: Activated endothelial cells proliferate and migrate toward the angiogenic stimulus, guided by chemotactic signals.  Tube Formation: Endothelial cells organize into tube-like structures, forming capillaries. This process involves the creation of lumens within the tubes.  Vessel Maturation: The newly formed vessels undergo maturation processes, including the recruitment of pericytes and smooth muscle cells. This maturation is crucial for the stability and functionality of the vasculature.  Integration with Circulatory System: The newly formed blood vessels integrate into the existing circulatory system, providing increased blood flow to the target tissues.   &nbsp;  Angiogenesis is regulated by both pro and anti-angiogenic factors. The most common pro angiogenic factors are VEGF and FGF (Folkman).  &nbsp;  Angiogenesis is a fundamental mechanism in development, tissue repair, and various pathological conditions, including cancer&nbsp;:     Development: During embryonic development, angiogenesis is critical for establishing the vascular network necessary for organ and tissue formation (Ribatti).  Tissue Repair and Regeneration: Angiogenesis plays a key role in tissue repair and regeneration after injury or damage. The formation of new blood vessels helps supply nutrients and oxygen to the healing tissue (Ribatti).  Menstrual Cycle and Pregnancy: In the female reproductive system, angiogenesis is a normal part of the menstrual cycle and is essential for the development of the placenta during pregnancy (Hoier).  Inflammatory Response: Angiogenesis is involved in the inflammatory response, facilitating the influx of immune cells to sites of infection or injury.  Cancer Growth and Metastasis&nbsp;: In cancer, angiogenesis is hijacked by tumors to support their growth and metastasis. Tumors release pro-angiogenic factors, promoting the formation of new blood vessels that supply nutrients and oxygen to the growing cancer cells (Nishida).  Ischemic Diseases: Angiogenesis is a therapeutic target in diseases involving inadequate blood supply, such as ischemic heart disease and peripheral artery disease (Ferrara)", "timestamp": "Fri May 15 21:42:25 +0000 2026"}