{"annotations": [{"id": ["mesh:D013196"], "is_neural_normalized": false, "mention": "DHT", "obj": "drug", "prob": 0.998167872428894, "span": {"begin": 89, "end": 92}}, {"id": ["CUI-less"], "is_neural_normalized": false, "mention": "T", "obj": "cell_line", "prob": 0.43756693601608276, "span": {"begin": 125, "end": 126}}, {"id": ["mesh:D013196"], "is_neural_normalized": false, "mention": "DHT", "obj": "drug", "prob": 0.9984495639801025, "span": {"begin": 202, "end": 205}}, {"id": ["NCBIGene:6715"], "is_neural_normalized": false, "mention": "5&alpha;-reductase", "obj": "gene", "prob": 0.9949219822883606, "span": {"begin": 290, "end": 308}}, {"id": ["mesh:D013196"], "is_neural_normalized": false, "mention": "DHT", "obj": "drug", "prob": 0.9973892569541931, "span": {"begin": 346, "end": 349}}, {"id": ["mesh:D013196"], "is_neural_normalized": false, "mention": "DHT", "obj": "drug", "prob": 0.9978850483894348, "span": {"begin": 461, "end": 464}}, {"id": ["mesh:D013196"], "is_neural_normalized": false, "mention": "DHT", "obj": "drug", "prob": 0.9979388117790222, "span": {"begin": 525, "end": 528}}, {"id": ["mesh:D013196"], "is_neural_normalized": false, "mention": "DHT", "obj": "drug", "prob": 0.9949038028717041, "span": {"begin": 622, "end": 625}}, {"id": ["mesh:D013196"], "is_neural_normalized": false, "mention": "DHT", "obj": "drug", "prob": 0.8562545776367188, "span": {"begin": 772, "end": 775}}, {"id": ["mesh:D013196"], "is_neural_normalized": false, "mention": "DHT", "obj": "drug", "prob": 0.9973345994949341, "span": {"begin": 900, "end": 903}}, {"id": ["mesh:D013196"], "is_neural_normalized": false, "mention": "DHT", "obj": "drug", "prob": 0.9952473044395447, "span": {"begin": 959, "end": 962}}, {"id": ["mesh:D013256"], "is_neural_normalized": false, "mention": "steroid", "obj": "drug", "prob": 0.9984540939331055, "span": {"begin": 989, "end": 996}}, {"id": ["NCBITaxon:9606"], "is_neural_normalized": false, "mention": "humans", "obj": "species", "prob": 0.9841746687889099, "span": {"begin": 1088, "end": 1094}}], "text": "The biological plausibility for this KER is considered high  It is well established that DHT is synthesized from circulating T. 5&alpha;-reductase is the enzyme responsible for the conversion of T into DHT. Multiple isoforms of this enzyme are expressed in different tissues. Expression of 5&alpha;-reductase in peripheral tissues dictates where DHT will be formed from circulating T (Azzouni et al., 2012; Swerdloff et al., 2017).  Since T can be converted to DHT, it stands to reason that a lack of T can lead to a lack of DHT. Therefore, if there is a marked reduction in the availability of T, it can be surmised that DHT levels are consequently affected. However, to what extent T needs to be diminished in tissues before there is a functionally relevant decrease in DHT is largely unknown. In addition, the quantitative relationship between substrate (T) availability and levels of synthesized DHT is not well characterized in tissues in vivo. Notably, DHT can be produced via other steroid intermediates through the &lsquo;backdoor pathway&rsquo; in mammals such as marsupials and humans (Renfree &amp; Shaw 2023).", "timestamp": "Mon Jun 08 15:17:00 +0000 2026"}