{"annotations": [{"id": ["mesh:D013963"], "is_neural_normalized": false, "mention": "Thyroid hormones", "obj": "drug", "prob": 0.8205241560935974, "span": {"begin": 0, "end": 16}}, {"id": ["NCBIGene:7068"], "is_neural_normalized": true, "mention": "thyroid hormone receptor alpha and beta", "obj": "gene", "prob": 0.9972588419914246, "span": {"begin": 492, "end": 531}}, {"id": ["NCBITaxon:7955"], "is_neural_normalized": false, "mention": "zebrafish", "obj": "species", "prob": 0.9420101642608643, "span": {"begin": 577, "end": 586}}], "text": "Thyroid hormones are known to be involved in development, especially in metamorphosis in amphibians and in embryonic-to-larval transition (Liu and Chan, 2002) and larval-to-juvenile transition (Brown et al., 1997) in fish. Inflation of the posterior chamber is part of the embryonic-to-larval transition in fish, together with structural and functional maturation of the mouth and gastrointestinal tract, and resorption of the yolk sac (Liu and Chan, 2002). Marelli et al. (2016) showed that thyroid hormone receptor alpha and beta are both expressed in swim bladder tissue of zebrafish at 5 days post fertilization, corresponding to the timing of posterior inflation. this time point has additionally been shown to coincide with increased T3 and T4 levels (Chang et al., 2012), suggesting that posterior inflation is under thyroid hormone regulation.", "timestamp": "Mon Jun 08 14:54:59 +0000 2026"}