{"annotations": [{"id": ["NCBITaxon:8022"], "is_neural_normalized": false, "mention": "Rainbow Trout", "obj": "species", "prob": 0.6498585939407349, "span": {"begin": 42, "end": 55}}, {"id": ["NCBIGene:43"], "is_neural_normalized": false, "mention": "AChE", "obj": "gene", "prob": 0.9929475784301758, "span": {"begin": 67, "end": 71}}, {"id": ["mesh:D010100"], "is_neural_normalized": false, "mention": "oxygen", "obj": "drug", "prob": 0.9993377327919006, "span": {"begin": 195, "end": 201}}, {"id": ["mesh:C001969"], "is_neural_normalized": false, "mention": "Acephate", "obj": "drug", "prob": 0.9988546371459961, "span": {"begin": 375, "end": 383}}, {"id": ["mesh:D005278"], "is_neural_normalized": false, "mention": "fenitrothion", "obj": "drug", "prob": 0.9990216493606567, "span": {"begin": 388, "end": 400}}, {"id": ["NCBITaxon:8022"], "is_neural_normalized": false, "mention": "rainbow trout", "obj": "species", "prob": 0.9815198183059692, "span": {"begin": 419, "end": 432}}], "text": "Data collected in experimental studies in Rainbow Trout found that AChE inhibition decreased heart rate and increased ventilation volume. However, in spite of the increase in ventilation volume, oxygen utilization remained low. Therefore, it is biologically plausible that reduced fluid flow through the gills leads to respiratory distress in fish (Duangsawasdi, 1977).      Acephate and fenitrothion exposure in adult rainbow trout resulted in decreased heart rate, increased ventilation rate and amplitude similarly characteristic to fish exposed to hypoxia. ECG after exposure showed irregular heart beats and changes in ECG waveforms (Duagsawasdi 1978, Duagsawasdi and Klaverkamp, 1979).", "timestamp": "Mon Jun 08 14:29:45 +0000 2026"}